<?xml version="1.0" encoding="UTF-8"?>
<objects serializationModel="Studio.02.02.00">
	<object class="AudioFile" id="{a5fabf0b-5cb7-4562-a74e-559a78ecb53b}">
		<property name="color">
			<value>Red</value>
		</property>
		<property name="assetPath">
			<value>Enemy/enemy_hit_04.wav</value>
		</property>
		<property name="frequencyInKHz">
			<value>48</value>
		</property>
		<property name="channelCount">
			<value>2</value>
		</property>
		<property name="length">
			<value>0.34999999999999998</value>
		</property>
		<relationship name="masterAssetFolder">
			<destination>{e46de09a-6a99-44e4-9561-328b5cfd4533}</destination>
		</relationship>
	</object>
</objects>
